[
  {
    "id": "1cTq9BTNbjg",
    "title": "4-Part Strength Workout Framework to Transform Your Body (FORGET EVERYTHING ELSE!)",
    "origin": "🇺🇸 アメリカ（Dr. Shannon Ritchey）"
  },
  {
    "id": "-lVb9GMYPS8",
    "title": "Russell Brand EXPLAINS How To FIND HAPPINESS & Start Living A Life Of PURPOSE | Jay Shetty",
    "origin": "🇬🇧 イングランド・エセックス"
  },
  {
    "id": "7md9c8MxIOs",
    "title": "Simon Sinek: The Most Incredible Thing You Can Do For A Loved One",
    "origin": "🇬🇧 ロンドン出身"
  },
  {
    "id": "lRMReor3hpg",
    "title": "Gordon Ramsay Exclusive: It’s Time To Tell My Full Story",
    "origin": "🇬🇧 スコットランド出身"
  },
  {
    "id": "IR_JOaYJnVE",
    "title": "Jay Shetty Interviews His Wife For The First Time | On Purpose Podcast Ep. 1",
    "origin": "🇬🇧 ロンドン出身（Radhi）"
  },
  {
    "id": "57XzeTZq99g",
    "title": "Cillian Murphy talks OPPENHEIMER, PEAKY BLINDERS, BATMAN, 28 DAYS LATER I Happy Sad Confused",
    "origin": "🇮🇪 アイルランド・コーク"
  },
  {
    "id": "UoBoD2xll1Y",
    "title": "Chris Moyles meets Liam Gallagher | Full Interview | Radio X",
    "origin": "🇬🇧 マンチェスター（Liam Gallagher・訛り強）"
  },
  {
    "id": "qCLtkm_6XcE",
    "title": "Sean Bean on ANEMONE, Daniel Day-Lewis, LORD OF THE RINGS, GAME OF THRONES, GOLDENEYE, PATRIOT GAMES",
    "origin": "🇬🇧 シェフィールド（Sean Bean・ヨークシャー訛り）"
  },
  {
    "id": "L22JpW6an-o",
    "title": "Kate Winslet talks AVATAR: THE WAY OF WATER, TITANIC, & more!",
    "origin": "🇬🇧 イングランド・レディング（Kate Winslet）"
  },
  {
    "id": "YhDmHzPw5lw",
    "title": "Elizabeth Olsen talks LOVE & DEATH, WANDAVISION, advice for Marvel actors: Happy Sad Confused",
    "origin": "🇺🇸 アメリカ・カリフォルニア（Elizabeth Olsen）"
  },
  {
    "id": "tdQjGUmO_3M",
    "title": "Bellingham & Rogers Talk Squad Quality & Team Bromances! | Ep. 5 | Lions' Den Connected by EE",
    "origin": "🇬🇧 イングランド（Bellingham ほか・サッカー）"
  },
  {
    "id": "AbgcHjDjMiM",
    "title": "EXCLUSIVE! Bukayo Saka and Declan Rice REACT to winning Premier League 🏆",
    "origin": "🇬🇧 ロンドン（Saka & Rice・サッカー）"
  },
  {
    "id": "o_B5vful8KQ",
    "title": "Lewis Capaldi | This Past Weekend w/ Theo Von #597",
    "origin": "🏴󠁧󠁢󠁳󠁣󠁴󠁿 スコットランド（Lewis Capaldi）"
  },
  {
    "id": "NFrajlWblAo",
    "title": "I Had To Lie About My Sexuality @CalumScottOfficial Reveals What REALLY Happened On @BGT!",
    "origin": "🇬🇧 イングランド・ハル（Calum Scott）"
  },
  {
    "id": "qnP5JfF_TOo",
    "title": "Beth Rigby Interviews... actor Liam Neeson",
    "origin": "🇮🇪 北アイルランド・バリミーナ（Liam Neeson・訛り強）"
  },
  {
    "id": "M-uyHpLhABk",
    "title": "Sam McBride and Fintan O’Toole: ‘There are good arguments for and against a united Ireland’ | BelTel",
    "origin": "🇮🇪 アイルランド（Sam McBride・Fintan O’Toole）"
  },
  {
    "id": "wRjVS4X3Wfo",
    "title": "First Minister of Northern Ireland Michelle O'Neill - Full Interview | The Late Late Show",
    "origin": "🇮🇪 北アイルランド・ティロン（Michelle O’Neill）"
  },
  {
    "id": "hRm7fS5BgY0",
    "title": "Different mentality between Japan and America｜The Austin and Arthur Show"
  }
]
